{
    "openapi": "3.0.0",
    "info": {
        "title": "Club deportivo API",
        "description": "API Reservas club deportivo, es  una pureba tecnica para la empresa NETSNITS ",
        "version": "1.0.0"
    },
    "servers": [
        {
            "url": "http://localhost:8000",
            "description": "API Reservas"
        },
        {
            "url": "http://localhost:8000",
            "description": "Class DeportesController"
        },
        {
            "url": "http://localhost:8000",
            "description": "Class PistasController"
        },
        {
            "url": "http://localhost:8000",
            "description": "Class ReservasController"
        },
        {
            "url": "http://localhost:8000",
            "description": "Class SociosController"
        },
        {
            "url": "http://localhost:8000"
        }
    ],
    "paths": {
        "/api/register": {
            "post": {
                "tags": [
                    "Usuarios"
                ],
                "summary": "Registrar un nuevo usuario",
                "operationId": "8a56853624e025573120a09a4c75d468",
                "requestBody": {
                    "description": "Datos para registrar un nuevo usuario",
                    "required": true,
                    "content": {
                        "application/json": {
                            "schema": {
                                "properties": {
                                    "email": {
                                        "type": "string",
                                        "format": "email",
                                        "example": "siphax@zerrouki.com"
                                    },
                                    "password": {
                                        "type": "string",
                                        "example": "12345678"
                                    },
                                    "password_confirmation": {
                                        "type": "string",
                                        "example": "12345678"
                                    }
                                },
                                "type": "object"
                            }
                        }
                    }
                },
                "responses": {
                    "201": {
                        "description": "Usuario registrado exitosamente",
                        "content": {
                            "application/json": {
                                "schema": {
                                    "properties": {
                                        "user": {
                                            "type": "object"
                                        },
                                        "token": {
                                            "type": "string",
                                            "example": "token_de_autenticacion"
                                        }
                                    },
                                    "type": "object"
                                }
                            }
                        }
                    }
                }
            }
        },
        "/api/login": {
            "post": {
                "tags": [
                    "Usuarios"
                ],
                "summary": "Iniciar sesión",
                "description": "Inicia sesión y devuelve un token de acceso.",
                "operationId": "a3b306d14572d1f4bd6c064b3233e7b8",
                "requestBody": {
                    "required": true,
                    "content": {
                        "application/json": {
                            "schema": {
                                "properties": {
                                    "email": {
                                        "type": "string",
                                        "format": "email",
                                        "example": "siphax@zerrouki.com"
                                    },
                                    "password": {
                                        "type": "string",
                                        "example": "12345678"
                                    }
                                },
                                "type": "object"
                            }
                        }
                    }
                },
                "responses": {
                    "201": {
                        "description": "Inicio de sesión exitoso",
                        "content": {
                            "application/json": {
                                "schema": {
                                    "properties": {
                                        "message": {
                                            "type": "string",
                                            "example": "Hola usuario@example.com"
                                        },
                                        "access_token": {
                                            "type": "string",
                                            "example": "token_de_acceso_generado"
                                        }
                                    },
                                    "type": "object"
                                }
                            }
                        }
                    },
                    "401": {
                        "description": "Credenciales no válidas",
                        "content": {
                            "application/json": {
                                "schema": {
                                    "properties": {
                                        "message": {
                                            "type": "string",
                                            "example": "Detalles de inicio de sesión no válidos"
                                        }
                                    },
                                    "type": "object"
                                }
                            }
                        }
                    }
                }
            }
        },
        "/api/logout": {
            "get": {
                "tags": [
                    "Usuarios"
                ],
                "summary": "Cerrar sesión",
                "description": "Cierra la sesión del usuario revocando todos los tokens de acceso.",
                "operationId": "3f19b742e4ead13f81ba0d6c0d46ac1b",
                "responses": {
                    "201": {
                        "description": "Cierre de sesión exitoso",
                        "content": {
                            "application/json": {
                                "schema": {
                                    "properties": {
                                        "message": {
                                            "type": "string",
                                            "example": "Cierre de sesión exitoso"
                                        }
                                    },
                                    "type": "object"
                                }
                            }
                        }
                    },
                    "401": {
                        "description": "No autorizado",
                        "content": {
                            "application/json": {
                                "schema": {
                                    "properties": {
                                        "message": {
                                            "type": "string",
                                            "example": "No se pudo cerrar sesión. Usuario no autenticado."
                                        }
                                    },
                                    "type": "object"
                                }
                            }
                        }
                    }
                },
                "security": [
                    {
                        "bearerAuth": []
                    }
                ]
            }
        },
        "/api/perfil": {
            "get": {
                "tags": [
                    "Usuarios"
                ],
                "summary": "Listar recursos",
                "description": "Muestra una lista de recursos.",
                "operationId": "4b21a78200b8ed460f84c66d4e7e0069",
                "responses": {
                    "200": {
                        "description": "Operación exitosa",
                        "content": {
                            "application/json": {
                                "schema": {
                                    "properties": {
                                        "user": {
                                            "description": "Información del usuario autenticado",
                                            "type": "object"
                                        }
                                    },
                                    "type": "object"
                                }
                            }
                        }
                    },
                    "401": {
                        "description": "No autorizado",
                        "content": {
                            "application/json": {
                                "schema": {
                                    "properties": {
                                        "message": {
                                            "type": "string",
                                            "example": "No autorizado para acceder a este recurso."
                                        }
                                    },
                                    "type": "object"
                                }
                            }
                        }
                    }
                },
                "security": [
                    {
                        "bearerAuth": []
                    }
                ]
            }
        },
        "/api/update": {
            "put": {
                "tags": [
                    "Usuarios"
                ],
                "summary": "Actualizar recurso",
                "description": "Actualiza el recurso especificado en el almacenamiento.",
                "operationId": "0533045b97c06136dcd13671333c81d4",
                "requestBody": {
                    "required": true,
                    "content": {
                        "application/json": {
                            "schema": {
                                "properties": {
                                    "email": {
                                        "type": "string",
                                        "format": "email",
                                        "example": "siphax@zerrouki.com"
                                    },
                                    "password": {
                                        "type": "string",
                                        "example": "12345678"
                                    },
                                    "newPassword": {
                                        "type": "string",
                                        "example": "nueva_contraseña"
                                    }
                                },
                                "type": "object"
                            }
                        }
                    }
                },
                "responses": {
                    "200": {
                        "description": "Contraseña actualizada exitosamente",
                        "content": {
                            "application/json": {
                                "schema": {
                                    "properties": {
                                        "message": {
                                            "type": "string",
                                            "example": "Contraseña actualizada exitosamente"
                                        }
                                    },
                                    "type": "object"
                                }
                            }
                        }
                    },
                    "401": {
                        "description": "No autorizado",
                        "content": {
                            "application/json": {
                                "schema": {
                                    "properties": {
                                        "error": {
                                            "type": "string",
                                            "example": "Contraseña actual incorrecta"
                                        }
                                    },
                                    "type": "object"
                                }
                            }
                        }
                    },
                    "422": {
                        "description": "Error de validación",
                        "content": {
                            "application/json": {
                                "schema": {
                                    "properties": {
                                        "error": {
                                            "type": "string",
                                            "example": "El formato de correo electrónico no es válido."
                                        }
                                    },
                                    "type": "object"
                                }
                            }
                        }
                    }
                },
                "security": [
                    {
                        "bearerAuth": []
                    }
                ]
            }
        },
        "/api/delete": {
            "delete": {
                "tags": [
                    "Usuarios"
                ],
                "summary": "Eliminar recurso",
                "description": "Elimina el recurso especificado del almacenamiento.",
                "operationId": "585da9399b44d61faae6f2e0f6b76e7d",
                "responses": {
                    "201": {
                        "description": "Usuario eliminado",
                        "content": {
                            "application/json": {
                                "schema": {
                                    "properties": {
                                        "message": {
                                            "type": "string",
                                            "example": "Usuario eliminado"
                                        }
                                    },
                                    "type": "object"
                                }
                            }
                        }
                    },
                    "401": {
                        "description": "No autorizado",
                        "content": {
                            "application/json": {
                                "schema": {
                                    "properties": {
                                        "error": {
                                            "type": "string",
                                            "example": "No se pudo eliminar el usuario. Usuario no autenticado."
                                        }
                                    },
                                    "type": "object"
                                }
                            }
                        }
                    }
                },
                "security": [
                    {
                        "bearerAuth": []
                    }
                ]
            }
        },
        "/api/deportes": {
            "get": {
                "tags": [
                    "Deportes"
                ],
                "summary": "Listar deportes",
                "description": "Muestra una lista de deportes.",
                "operationId": "bfc9292a97ee7de249901347afd231ce",
                "responses": {
                    "201": {
                        "description": "Operación exitosa",
                        "content": {
                            "application/json": {
                                "schema": {
                                    "properties": {
                                        "deportes": {
                                            "type": "array",
                                            "items": {
                                                "properties": {
                                                    "id": {
                                                        "type": "integer"
                                                    },
                                                    "deporte": {
                                                        "type": "string"
                                                    }
                                                },
                                                "type": "object"
                                            }
                                        }
                                    },
                                    "type": "object"
                                }
                            }
                        }
                    },
                    "500": {
                        "description": "Error interno del servidor",
                        "content": {
                            "application/json": {
                                "schema": {
                                    "properties": {
                                        "error": {
                                            "type": "string",
                                            "example": "Mensaje de error interno"
                                        }
                                    },
                                    "type": "object"
                                }
                            }
                        }
                    }
                },
                "security": [
                    {
                        "bearerAuth": []
                    }
                ]
            },
            "put": {
                "tags": [
                    "Deportes"
                ],
                "summary": "Actualizar deporte",
                "description": "Actualiza el recurso de deporte especificado en el almacenamiento.",
                "operationId": "0498849f942c67966df8bc3ef592dcbb",
                "requestBody": {
                    "required": true,
                    "content": {
                        "application/json": {
                            "schema": {
                                "properties": {
                                    "id": {
                                        "type": "integer",
                                        "example": "1"
                                    },
                                    "nuevoDeporte": {
                                        "type": "string",
                                        "example": "Nuevo Deporte"
                                    }
                                },
                                "type": "object"
                            }
                        }
                    }
                },
                "responses": {
                    "201": {
                        "description": "Deporte modificado correctamente",
                        "content": {
                            "application/json": {
                                "schema": {
                                    "properties": {
                                        "message": {
                                            "type": "string",
                                            "example": "Nuevo Deporte modificado correctamente"
                                        }
                                    },
                                    "type": "object"
                                }
                            }
                        }
                    },
                    "404": {
                        "description": "Deporte no encontrado",
                        "content": {
                            "application/json": {
                                "schema": {
                                    "properties": {
                                        "message": {
                                            "type": "string",
                                            "example": "Deporte no encontrado"
                                        }
                                    },
                                    "type": "object"
                                }
                            }
                        }
                    },
                    "422": {
                        "description": "Error de validación",
                        "content": {
                            "application/json": {
                                "schema": {
                                    "properties": {
                                        "error": {
                                            "type": "string",
                                            "example": "El campo nuevoDeporte debe ser una cadena con un máximo de 50 caracteres."
                                        }
                                    },
                                    "type": "object"
                                }
                            }
                        }
                    },
                    "500": {
                        "description": "Error interno del servidor",
                        "content": {
                            "application/json": {
                                "schema": {
                                    "properties": {
                                        "error": {
                                            "type": "string",
                                            "example": "Mensaje de error interno"
                                        }
                                    },
                                    "type": "object"
                                }
                            }
                        }
                    }
                },
                "security": [
                    {
                        "bearerAuth": []
                    }
                ]
            },
            "post": {
                "tags": [
                    "Deportes"
                ],
                "summary": "Crear deporte",
                "description": "Almacena un nuevo recurso de deporte en el almacenamiento.",
                "operationId": "a5c4acdceb1bc5c6d737c5018e98973f",
                "requestBody": {
                    "required": true,
                    "content": {
                        "application/json": {
                            "schema": {
                                "properties": {
                                    "deporte": {
                                        "type": "string",
                                        "example": "Nuevo Deporte"
                                    }
                                },
                                "type": "object"
                            }
                        }
                    }
                },
                "responses": {
                    "201": {
                        "description": "Deporte creado correctamente",
                        "content": {
                            "application/json": {
                                "schema": {
                                    "properties": {
                                        "message": {
                                            "type": "string",
                                            "example": "Deporte Nuevo Deporte creado correctamente"
                                        }
                                    },
                                    "type": "object"
                                }
                            }
                        }
                    },
                    "422": {
                        "description": "Error de validación",
                        "content": {
                            "application/json": {
                                "schema": {
                                    "properties": {
                                        "error": {
                                            "type": "string",
                                            "example": "El campo deporte debe ser único."
                                        }
                                    },
                                    "type": "object"
                                }
                            }
                        }
                    },
                    "500": {
                        "description": "Error interno del servidor",
                        "content": {
                            "application/json": {
                                "schema": {
                                    "properties": {
                                        "error": {
                                            "type": "string",
                                            "example": "Mensaje de error interno"
                                        }
                                    },
                                    "type": "object"
                                }
                            }
                        }
                    }
                },
                "security": [
                    {
                        "bearerAuth": []
                    }
                ]
            },
            "delete": {
                "tags": [
                    "Deportes"
                ],
                "summary": "Eliminar deporte",
                "description": "Elimina el recurso de deporte especificado en el almacenamiento y las pistas asociadas.",
                "operationId": "eaf7c791beda1311981fbf6983b74eec",
                "requestBody": {
                    "required": true,
                    "content": {
                        "application/json": {
                            "schema": {
                                "properties": {
                                    "id": {
                                        "type": "integer",
                                        "example": "1"
                                    }
                                },
                                "type": "object"
                            }
                        }
                    }
                },
                "responses": {
                    "201": {
                        "description": "Deporte eliminado correctamente",
                        "content": {
                            "application/json": {
                                "schema": {
                                    "properties": {
                                        "message": {
                                            "type": "string",
                                            "example": "Deporte eliminado correctamente && Pistas eliminadas correctamente"
                                        }
                                    },
                                    "type": "object"
                                }
                            }
                        }
                    },
                    "404": {
                        "description": "Deporte no eliminado correctamente",
                        "content": {
                            "application/json": {
                                "schema": {
                                    "properties": {
                                        "error": {
                                            "type": "string",
                                            "example": "Deporte no eliminado correctamente"
                                        }
                                    },
                                    "type": "object"
                                }
                            }
                        }
                    },
                    "422": {
                        "description": "Error de validación",
                        "content": {
                            "application/json": {
                                "schema": {
                                    "properties": {
                                        "error": {
                                            "type": "string",
                                            "example": "El campo id debe ser un número entero válido."
                                        }
                                    },
                                    "type": "object"
                                }
                            }
                        }
                    },
                    "500": {
                        "description": "Error interno del servidor",
                        "content": {
                            "application/json": {
                                "schema": {
                                    "properties": {
                                        "error": {
                                            "type": "string",
                                            "example": "Mensaje de error interno"
                                        }
                                    },
                                    "type": "object"
                                }
                            }
                        }
                    }
                },
                "security": [
                    {
                        "bearerAuth": []
                    }
                ]
            }
        },
        "/api/pistas": {
            "get": {
                "tags": [
                    "Pistas"
                ],
                "summary": "Listar pistas",
                "description": "Muestra una lista de pistas.",
                "operationId": "6dd87f3224e87c5e8f642f27e84ff8b8",
                "responses": {
                    "201": {
                        "description": "Operación exitosa",
                        "content": {
                            "application/json": {
                                "schema": {
                                    "properties": {
                                        "pistas": {
                                            "type": "array",
                                            "items": {
                                                "properties": {
                                                    "id": {
                                                        "type": "integer"
                                                    },
                                                    "pista": {
                                                        "type": "string"
                                                    }
                                                },
                                                "type": "object"
                                            }
                                        }
                                    },
                                    "type": "object"
                                }
                            }
                        }
                    },
                    "500": {
                        "description": "Error interno del servidor",
                        "content": {
                            "application/json": {
                                "schema": {
                                    "properties": {
                                        "error": {
                                            "type": "string",
                                            "example": "Mensaje de error interno"
                                        }
                                    },
                                    "type": "object"
                                }
                            }
                        }
                    }
                },
                "security": [
                    {
                        "bearerAuth": []
                    }
                ]
            },
            "put": {
                "tags": [
                    "Pistas"
                ],
                "summary": "Actualizar pista",
                "description": "Actualiza el recurso de pista especificado en el almacenamiento.",
                "operationId": "6f29d8598f247f6dfa3691dacc7e0942",
                "requestBody": {
                    "required": true,
                    "content": {
                        "application/json": {
                            "schema": {
                                "properties": {
                                    "id": {
                                        "type": "integer",
                                        "example": "1"
                                    },
                                    "pista": {
                                        "type": "string",
                                        "example": "Nueva Pista"
                                    }
                                },
                                "type": "object"
                            }
                        }
                    }
                },
                "responses": {
                    "201": {
                        "description": "Pista actualizada correctamente",
                        "content": {
                            "application/json": {
                                "schema": {
                                    "properties": {
                                        "message": {
                                            "type": "string",
                                            "example": "Nueva Pista actualizada correctamente"
                                        }
                                    },
                                    "type": "object"
                                }
                            }
                        }
                    },
                    "404": {
                        "description": "No existe la pista",
                        "content": {
                            "application/json": {
                                "schema": {
                                    "properties": {
                                        "message": {
                                            "type": "string",
                                            "example": "No existe la pista"
                                        }
                                    },
                                    "type": "object"
                                }
                            }
                        }
                    },
                    "422": {
                        "description": "Error de validación",
                        "content": {
                            "application/json": {
                                "schema": {
                                    "properties": {
                                        "error": {
                                            "type": "string",
                                            "example": "El campo pista debe tener un máximo de 50 caracteres."
                                        }
                                    },
                                    "type": "object"
                                }
                            }
                        }
                    },
                    "500": {
                        "description": "Error interno del servidor",
                        "content": {
                            "application/json": {
                                "schema": {
                                    "properties": {
                                        "error": {
                                            "type": "string",
                                            "example": "Mensaje de error interno"
                                        }
                                    },
                                    "type": "object"
                                }
                            }
                        }
                    }
                },
                "security": [
                    {
                        "bearerAuth": []
                    }
                ]
            },
            "post": {
                "tags": [
                    "Pistas"
                ],
                "summary": "Crear pista",
                "description": "Almacena un nuevo recurso de pista en el almacenamiento.",
                "operationId": "5fdd45c5fcc4f21781c5575945f47502",
                "requestBody": {
                    "required": true,
                    "content": {
                        "application/json": {
                            "schema": {
                                "properties": {
                                    "pista": {
                                        "type": "string",
                                        "example": "Nueva Pista"
                                    }
                                },
                                "type": "object"
                            }
                        }
                    }
                },
                "responses": {
                    "201": {
                        "description": "Pista creada correctamente",
                        "content": {
                            "application/json": {
                                "schema": {
                                    "properties": {
                                        "message": {
                                            "type": "string",
                                            "example": "Pista Nueva Pista creada correctamente"
                                        }
                                    },
                                    "type": "object"
                                }
                            }
                        }
                    },
                    "422": {
                        "description": "Error de validación",
                        "content": {
                            "application/json": {
                                "schema": {
                                    "properties": {
                                        "error": {
                                            "type": "string",
                                            "example": "El campo pista debe ser único."
                                        }
                                    },
                                    "type": "object"
                                }
                            }
                        }
                    },
                    "500": {
                        "description": "Error interno del servidor",
                        "content": {
                            "application/json": {
                                "schema": {
                                    "properties": {
                                        "error": {
                                            "type": "string",
                                            "example": "Mensaje de error interno"
                                        }
                                    },
                                    "type": "object"
                                }
                            }
                        }
                    }
                },
                "security": [
                    {
                        "bearerAuth": []
                    }
                ]
            },
            "delete": {
                "tags": [
                    "Pistas"
                ],
                "summary": "Eliminar pista",
                "description": "Elimina el recurso de pista y su deporte asociado en el almacenamiento.",
                "operationId": "37676ba45c2e033c04550e0f12633b20",
                "requestBody": {
                    "required": true,
                    "content": {
                        "application/json": {
                            "schema": {
                                "properties": {
                                    "id": {
                                        "type": "integer",
                                        "example": "1"
                                    }
                                },
                                "type": "object"
                            }
                        }
                    }
                },
                "responses": {
                    "201": {
                        "description": "Pista y deporte eliminados correctamente",
                        "content": {
                            "application/json": {
                                "schema": {
                                    "properties": {
                                        "message": {
                                            "type": "string",
                                            "example": "Pista [Nombre de la pista] de deporte [Nombre del deporte] eliminada correctamente"
                                        }
                                    },
                                    "type": "object"
                                }
                            }
                        }
                    },
                    "404": {
                        "description": "No existe la pista o el deporte",
                        "content": {
                            "application/json": {
                                "schema": {
                                    "properties": {
                                        "message": {
                                            "type": "string",
                                            "example": "No existe la pista o el deporte"
                                        }
                                    },
                                    "type": "object"
                                }
                            }
                        }
                    },
                    "422": {
                        "description": "Error de validación",
                        "content": {
                            "application/json": {
                                "schema": {
                                    "properties": {
                                        "error": {
                                            "type": "string",
                                            "example": "El campo id debe ser un número entero válido."
                                        }
                                    },
                                    "type": "object"
                                }
                            }
                        }
                    },
                    "500": {
                        "description": "Error interno del servidor",
                        "content": {
                            "application/json": {
                                "schema": {
                                    "properties": {
                                        "error": {
                                            "type": "string",
                                            "example": "Mensaje de error interno"
                                        }
                                    },
                                    "type": "object"
                                }
                            }
                        }
                    }
                },
                "security": [
                    {
                        "bearerAuth": []
                    }
                ]
            }
        },
        "/api/reservas/search": {
            "post": {
                "tags": [
                    "Reservas"
                ],
                "summary": "buscar reservas",
                "description": "Muestra una busqueda de reservas basada en la fecha especificada ex 2023-11-20",
                "operationId": "1a6928e2c28c7fe6624c14d7c5074611",
                "parameters": [
                    {
                        "name": "fecha",
                        "in": "query",
                        "description": "Fecha en formato 'Y-m-d' (ejemplo: '2023-01-01')",
                        "required": true,
                        "schema": {
                            "type": "string",
                            "format": "date"
                        }
                    }
                ],
                "requestBody": {
                    "required": true,
                    "content": {
                        "application/json": {
                            "schema": {
                                "required": [
                                    "fecha"
                                ],
                                "properties": {
                                    "fecha": {
                                        "type": "string",
                                        "format": "date",
                                        "example": "2023-11-20"
                                    }
                                },
                                "type": "object"
                            }
                        }
                    }
                },
                "responses": {
                    "201": {
                        "description": "Operación exitosa",
                        "content": {
                            "application/json": {
                                "schema": {
                                    "properties": {
                                        "reservas": {
                                            "type": "array",
                                            "items": {
                                                "properties": {
                                                    "id": {
                                                        "type": "integer"
                                                    },
                                                    "reserva": {
                                                        "type": "array",
                                                        "items": {
                                                            "properties": {
                                                                "socio": {
                                                                    "type": "string"
                                                                },
                                                                "pista": {
                                                                    "type": "string"
                                                                },
                                                                "deporte": {
                                                                    "type": "string"
                                                                },
                                                                "fecha": {
                                                                    "type": "string",
                                                                    "format": "date"
                                                                },
                                                                "horaInicio": {
                                                                    "type": "string",
                                                                    "format": "time"
                                                                },
                                                                "horaFin": {
                                                                    "type": "string",
                                                                    "format": "time"
                                                                }
                                                            },
                                                            "type": "object"
                                                        }
                                                    }
                                                },
                                                "type": "object"
                                            }
                                        }
                                    },
                                    "type": "object"
                                }
                            }
                        }
                    },
                    "422": {
                        "description": "Error de validación",
                        "content": {
                            "application/json": {
                                "schema": {
                                    "properties": {
                                        "error": {
                                            "type": "string",
                                            "example": "El campo fecha debe tener el formato 'Y-m-d'."
                                        }
                                    },
                                    "type": "object"
                                }
                            }
                        }
                    },
                    "500": {
                        "description": "Error interno del servidor",
                        "content": {
                            "application/json": {
                                "schema": {
                                    "properties": {
                                        "error": {
                                            "type": "string",
                                            "example": "Mensaje de error interno"
                                        }
                                    },
                                    "type": "object"
                                }
                            }
                        }
                    }
                },
                "security": [
                    {
                        "bearerAuth": []
                    }
                ]
            }
        },
        "/api/reservas": {
            "put": {
                "tags": [
                    "Reservas"
                ],
                "summary": "Actualizar reserva",
                "description": "Actualiza el recurso de reserva especificado en el almacenamiento.",
                "operationId": "d51e7260d8c6615c711c1e7f25c4ee5c",
                "requestBody": {
                    "required": true,
                    "content": {
                        "application/json": {
                            "schema": {
                                "properties": {
                                    "reservaId": {
                                        "type": "integer",
                                        "example": "1"
                                    },
                                    "nuevaHora": {
                                        "type": "hour",
                                        "example": "10:00"
                                    }
                                },
                                "type": "object"
                            }
                        }
                    }
                },
                "responses": {
                    "201": {
                        "description": "Reserva actualizada correctamente",
                        "content": {
                            "application/json": {
                                "schema": {
                                    "properties": {
                                        "message": {
                                            "type": "string",
                                            "example": "Reserva actualizada a 10:00 con éxito."
                                        }
                                    },
                                    "type": "object"
                                }
                            }
                        }
                    },
                    "404": {
                        "description": "No se encontró ninguna reserva para actualizar",
                        "content": {
                            "application/json": {
                                "schema": {
                                    "properties": {
                                        "error": {
                                            "type": "string",
                                            "example": "No se encontró ninguna reserva para actualizar."
                                        }
                                    },
                                    "type": "object"
                                }
                            }
                        }
                    },
                    "422": {
                        "description": "Error de validación",
                        "content": {
                            "application/json": {
                                "schema": {
                                    "properties": {
                                        "error": {
                                            "type": "string",
                                            "example": "El campo nuevaHora debe tener el formato 'H:00'."
                                        }
                                    },
                                    "type": "object"
                                }
                            }
                        }
                    },
                    "500": {
                        "description": "Error interno del servidor",
                        "content": {
                            "application/json": {
                                "schema": {
                                    "properties": {
                                        "error": {
                                            "type": "string",
                                            "example": "Mensaje de error interno"
                                        }
                                    },
                                    "type": "object"
                                }
                            }
                        }
                    }
                },
                "security": [
                    {
                        "bearerAuth": []
                    }
                ]
            },
            "post": {
                "tags": [
                    "Reservas"
                ],
                "summary": "Crear reserva",
                "description": "Almacena un nuevo recurso de reserva en el almacenamiento.",
                "operationId": "3d9252887263d661d869b88882ad7660",
                "requestBody": {
                    "required": true,
                    "content": {
                        "application/json": {
                            "schema": {
                                "properties": {
                                    "pista_id": {
                                        "type": "integer",
                                        "example": "1"
                                    },
                                    "horaInicio": {
                                        "type": "hour",
                                        "example": "08:00"
                                    }
                                },
                                "type": "object"
                            }
                        }
                    }
                },
                "responses": {
                    "201": {
                        "description": "Reserva creada correctamente",
                        "content": {
                            "application/json": {
                                "schema": {
                                    "properties": {
                                        "reserva": {
                                            "type": "array",
                                            "items": {
                                                "properties": {
                                                    "userId": {
                                                        "type": "integer"
                                                    },
                                                    "socio_id": {
                                                        "type": "integer"
                                                    },
                                                    "pista_id": {
                                                        "type": "integer"
                                                    },
                                                    "socio": {
                                                        "type": "string"
                                                    },
                                                    "pista": {
                                                        "type": "string"
                                                    },
                                                    "deporte": {
                                                        "type": "integer"
                                                    },
                                                    "fecha": {
                                                        "type": "string",
                                                        "format": "date"
                                                    },
                                                    "horaInicio": {
                                                        "type": "string",
                                                        "format": "time"
                                                    },
                                                    "horaFin": {
                                                        "type": "string",
                                                        "format": "time"
                                                    }
                                                },
                                                "type": "object"
                                            }
                                        }
                                    },
                                    "type": "object"
                                }
                            }
                        }
                    },
                    "400": {
                        "description": "La hora de inicio debe estar entre las 08:00 y las 22:00",
                        "content": {
                            "application/json": {
                                "schema": {
                                    "properties": {
                                        "error": {
                                            "type": "string",
                                            "example": "La hora de inicio debe estar entre las 08:00 y las 22:00"
                                        }
                                    },
                                    "type": "object"
                                }
                            }
                        }
                    },
                    "422": {
                        "description": "No puedes realizar más de 3 reservas en un mismo día.",
                        "content": {
                            "application/json": {
                                "schema": {
                                    "properties": {
                                        "error": {
                                            "type": "string",
                                            "example": "No puedes realizar más de 3 reservas en un mismo día."
                                        }
                                    },
                                    "type": "object"
                                }
                            }
                        }
                    },
                    "500": {
                        "description": "Error interno del servidor",
                        "content": {
                            "application/json": {
                                "schema": {
                                    "properties": {
                                        "error": {
                                            "type": "string",
                                            "example": "Mensaje de error interno"
                                        }
                                    },
                                    "type": "object"
                                }
                            }
                        }
                    }
                },
                "security": [
                    {
                        "bearerAuth": []
                    }
                ]
            },
            "delete": {
                "tags": [
                    "Reservas"
                ],
                "summary": "Eliminar reserva",
                "description": "Elimina el recurso de reserva especificado del almacenamiento.",
                "operationId": "c46f94a455fe0f2c235420929ffd7e8e",
                "responses": {
                    "201": {
                        "description": "Reserva eliminada correctamente",
                        "content": {
                            "application/json": {
                                "schema": {
                                    "properties": {
                                        "message": {
                                            "type": "string",
                                            "example": "Reserva eliminada con éxito."
                                        }
                                    },
                                    "type": "object"
                                }
                            }
                        }
                    },
                    "404": {
                        "description": "No se encontró ninguna reserva para eliminar",
                        "content": {
                            "application/json": {
                                "schema": {
                                    "properties": {
                                        "error": {
                                            "type": "string",
                                            "example": "No se encontró ninguna reserva para eliminar."
                                        }
                                    },
                                    "type": "object"
                                }
                            }
                        }
                    },
                    "500": {
                        "description": "Error interno del servidor",
                        "content": {
                            "application/json": {
                                "schema": {
                                    "properties": {
                                        "error": {
                                            "type": "string",
                                            "example": "Mensaje de error interno"
                                        }
                                    },
                                    "type": "object"
                                }
                            }
                        }
                    }
                },
                "security": [
                    {
                        "bearerAuth": []
                    }
                ]
            }
        },
        "/api/socios": {
            "get": {
                "tags": [
                    "Socios"
                ],
                "summary": "Listar socios",
                "description": "Muestra un listado de los recursos de socios.",
                "operationId": "569b4f5a1146387d72c7b7178b6e1bfc",
                "responses": {
                    "201": {
                        "description": "Listado de socios obtenido correctamente",
                        "content": {
                            "application/json": {
                                "schema": {
                                    "properties": {
                                        "socios": {
                                            "type": "array",
                                            "items": {
                                                "properties": {
                                                    "id": {
                                                        "type": "integer"
                                                    },
                                                    "nombre": {
                                                        "type": "string"
                                                    }
                                                },
                                                "type": "object"
                                            }
                                        }
                                    },
                                    "type": "object"
                                }
                            }
                        }
                    },
                    "500": {
                        "description": "Error interno del servidor",
                        "content": {
                            "application/json": {
                                "schema": {
                                    "properties": {
                                        "error": {
                                            "type": "string",
                                            "example": "Mensaje de error interno"
                                        }
                                    },
                                    "type": "object"
                                }
                            }
                        }
                    }
                },
                "security": [
                    {
                        "bearerAuth": []
                    }
                ]
            },
            "put": {
                "tags": [
                    "Socios"
                ],
                "summary": "Actualizar socio",
                "description": "Actualiza el recurso de socio especificado en el almacenamiento.",
                "operationId": "74ec5b14de4f33b6ab29d7e92dc42ba8",
                "requestBody": {
                    "required": true,
                    "content": {
                        "application/json": {
                            "schema": {
                                "properties": {
                                    "socioId": {
                                        "type": "integer",
                                        "example": "1"
                                    },
                                    "nombre": {
                                        "type": "string",
                                        "example": "John"
                                    },
                                    "apellidos": {
                                        "type": "string",
                                        "example": "Doe"
                                    }
                                },
                                "type": "object"
                            }
                        }
                    }
                },
                "responses": {
                    "201": {
                        "description": "Socio actualizado correctamente",
                        "content": {
                            "application/json": {
                                "schema": {
                                    "properties": {
                                        "message": {
                                            "type": "string",
                                            "example": "Socio actualizado correctamente"
                                        }
                                    },
                                    "type": "object"
                                }
                            }
                        }
                    },
                    "422": {
                        "description": "Error de validación",
                        "content": {
                            "application/json": {
                                "schema": {
                                    "properties": {
                                        "error": {
                                            "type": "string",
                                            "example": "Mensaje de error de validación"
                                        }
                                    },
                                    "type": "object"
                                }
                            }
                        }
                    },
                    "500": {
                        "description": "Error interno del servidor",
                        "content": {
                            "application/json": {
                                "schema": {
                                    "properties": {
                                        "error": {
                                            "type": "string",
                                            "example": "Mensaje de error interno"
                                        }
                                    },
                                    "type": "object"
                                }
                            }
                        }
                    },
                    "404": {
                        "description": "Socio no encontrado",
                        "content": {
                            "application/json": {
                                "schema": {
                                    "properties": {
                                        "error": {
                                            "type": "string",
                                            "example": "Socio no encontrado"
                                        }
                                    },
                                    "type": "object"
                                }
                            }
                        }
                    }
                },
                "security": [
                    {
                        "bearerAuth": []
                    }
                ]
            },
            "post": {
                "tags": [
                    "Socios"
                ],
                "summary": "Crear socio",
                "description": "Almacena un nuevo recurso de socio en el almacenamiento.",
                "operationId": "3e32561a2af457d577207c093adcd185",
                "requestBody": {
                    "required": true,
                    "content": {
                        "application/json": {
                            "schema": {
                                "properties": {
                                    "nombre": {
                                        "type": "string",
                                        "example": "John"
                                    },
                                    "apellidos": {
                                        "type": "string",
                                        "example": "Doe"
                                    }
                                },
                                "type": "object"
                            }
                        }
                    }
                },
                "responses": {
                    "201": {
                        "description": "Socio creado correctamente",
                        "content": {
                            "application/json": {
                                "schema": {
                                    "properties": {
                                        "message": {
                                            "type": "string",
                                            "example": "Socio creado correctamente"
                                        }
                                    },
                                    "type": "object"
                                }
                            }
                        }
                    },
                    "422": {
                        "description": "Error de validación",
                        "content": {
                            "application/json": {
                                "schema": {
                                    "properties": {
                                        "error": {
                                            "type": "string",
                                            "example": "Mensaje de error de validación"
                                        }
                                    },
                                    "type": "object"
                                }
                            }
                        }
                    },
                    "500": {
                        "description": "Error interno del servidor",
                        "content": {
                            "application/json": {
                                "schema": {
                                    "properties": {
                                        "error": {
                                            "type": "string",
                                            "example": "Mensaje de error interno"
                                        }
                                    },
                                    "type": "object"
                                }
                            }
                        }
                    }
                },
                "security": [
                    {
                        "bearerAuth": []
                    }
                ]
            },
            "delete": {
                "tags": [
                    "Socios"
                ],
                "summary": "Eliminar socio",
                "description": "Elimina el recurso de socio especificado del almacenamiento.",
                "operationId": "a2ffa7903362a271e99e6d414c970bf1",
                "requestBody": {
                    "required": true,
                    "content": {
                        "application/json": {
                            "schema": {
                                "properties": {
                                    "id": {
                                        "type": "integer",
                                        "example": "1"
                                    }
                                },
                                "type": "object"
                            }
                        }
                    }
                },
                "responses": {
                    "201": {
                        "description": "Socio eliminado correctamente",
                        "content": {
                            "application/json": {
                                "schema": {
                                    "properties": {
                                        "message": {
                                            "type": "string",
                                            "example": "Socio eliminado correctamente"
                                        }
                                    },
                                    "type": "object"
                                }
                            }
                        }
                    },
                    "422": {
                        "description": "Error de validación",
                        "content": {
                            "application/json": {
                                "schema": {
                                    "properties": {
                                        "error": {
                                            "type": "string",
                                            "example": "Mensaje de error de validación"
                                        }
                                    },
                                    "type": "object"
                                }
                            }
                        }
                    },
                    "500": {
                        "description": "Error interno del servidor",
                        "content": {
                            "application/json": {
                                "schema": {
                                    "properties": {
                                        "error": {
                                            "type": "string",
                                            "example": "Mensaje de error interno"
                                        }
                                    },
                                    "type": "object"
                                }
                            }
                        }
                    },
                    "404": {
                        "description": "Socio no encontrado",
                        "content": {
                            "application/json": {
                                "schema": {
                                    "properties": {
                                        "error": {
                                            "type": "string",
                                            "example": "Socio no encontrado"
                                        }
                                    },
                                    "type": "object"
                                }
                            }
                        }
                    }
                },
                "security": [
                    {
                        "bearerAuth": []
                    }
                ]
            }
        }
    },
    "components": {
        "securitySchemes": {
            "bearerAuth": {
                "type": "http",
                "bearerFormat": "JWT",
                "scheme": "bearer"
            }
        }
    }
}
